{
  "title": "Sinner of the Azure Abyss",
  "description": "For many centuries, merfolk have lived in the depths of the ocean—4,000 meters below the surface—where humanity cannot find them.\nHowever, one mermaid's life is turned upside-down when her best friend falls for a human.\n\n[MangaDex page](https://mangadex.org/title/1409de42-374a-4ff5-8a2f-0a7041f48ed5/abyss-azure-no-zainin?tab=chapters)\n",
  "artist": "Tomi Akihito",
  "author": "Tomi Akihito",
  "cover": "https://mangadex.org/covers/1409de42-374a-4ff5-8a2f-0a7041f48ed5/b9bc6718-7cfa-4e17-873a-717ac96b235f.jpg",
  "chapters": {
    "14": {
      "title": "14",
      "volume": "3",
      "last_updated": "1709961495",
      "groups": {
        "Last Hope Machine Translations": "/proxy/api/imgchest/chapter/9249aakg27n"
      }
    },
    "15": {
      "title": "15",
      "volume": "3",
      "last_updated": "1710110404",
      "groups": {
        "Last Hope Machine Translations": "/proxy/api/imgchest/chapter/lqyevvbgx7d"
      }
    },
    "16": {
      "title": "16",
      "volume": "3",
      "last_updated": "1710283858",
      "groups": {
        "Last Hope Machine Translations": "/proxy/api/imgchest/chapter/bp458d2xq45"
      }
    },
    "17": {
      "title": "17",
      "volume": "3",
      "last_updated": "1710364828",
      "groups": {
        "Last Hope Machine Translations": "/proxy/api/imgchest/chapter/md7olj8p97p"
      }
    },
    "18": {
      "title": "18",
      "volume": "3",
      "last_updated": "1710459920",
      "groups": {
        "Last Hope Machine Translations": "/proxy/api/imgchest/chapter/m9yxv29d64q"
      }
    },
    "19": {
      "title": "19",
      "volume": "3",
      "last_updated": "1710536699",
      "groups": {
        "Last Hope Machine Translations": "/proxy/api/imgchest/chapter/vj4j3vzw5y8"
      }
    }
  }
}